{"cameraMode":{"drawMode":0,"name":"Shaded","section":"Shading Mode"},"sceneLighting":true,"audioPlay":false,"sceneViewState":{"showFog":true,"showMaterialUpdate":false,"showSkybox":true,"showFlares":true,"showImageEffects":true,"showParticleSystems":true},"in2DMode":false,"pivot":{"x":11.568985939025879,"y":-132.02182006835938,"z":109.60257720947266},"rotation":{"x":0.4538823664188385,"y":0.025382844731211664,"z":-0.012942176312208176,"w":0.8906354308128357},"size":221.79454040527345,"orthographic":false}