{"cameraMode":{"drawMode":0,"name":"Shaded","section":"Shading Mode"},"sceneLighting":true,"audioPlay":false,"sceneViewState":{"showFog":true,"showMaterialUpdate":false,"showSkybox":true,"showFlares":true,"showImageEffects":true,"showParticleSystems":true},"in2DMode":false,"pivot":{"x":-102.08805084228516,"y":-133.33473205566407,"z":225.35272216796876},"rotation":{"x":-0.3365006744861603,"y":0.3137698471546173,"z":-0.12000282853841782,"w":-0.8798915147781372},"size":225.48423767089845,"orthographic":false}